[
  {
    "user_id": "26130933309908891",
    "phone": null,
    "has_phone": false
  },
  {
    "user_id": "26679113845055499",
    "phone": null,
    "has_phone": false
  },
  {
    "user_id": "26489961637281377",
    "phone": null,
    "has_phone": false
  },
  {
    "user_id": "26487687660843216",
    "phone": null,
    "has_phone": false
  },
  {
    "user_id": "34975009272115046",
    "phone": null,
    "has_phone": false
  },
  {
    "user_id": "27295789976690938",
    "phone": null,
    "has_phone": false
  },
  {
    "user_id": "26912744834978499",
    "phone": null,
    "has_phone": false
  },
  {
    "user_id": "26428492510140484",
    "phone": null,
    "has_phone": false
  },
  {
    "user_id": "26027763976922812",
    "phone": null,
    "has_phone": false
  },
  {
    "user_id": "26319174181073508",
    "phone": null,
    "has_phone": false
  },
  {
    "user_id": "25881635691515530",
    "phone": null,
    "has_phone": false
  },
  {
    "user_id": "26338971679099798",
    "phone": null,
    "has_phone": false
  },
  {
    "user_id": "35574813448770502",
    "phone": null,
    "has_phone": false
  },
  {
    "user_id": "26166766043008419",
    "phone": null,
    "has_phone": false
  },
  {
    "user_id": "26234828602864556",
    "phone": null,
    "has_phone": false
  },
  {
    "user_id": "34896254503352380",
    "phone": null,
    "has_phone": false
  },
  {
    "user_id": "26469340596009607",
    "phone": null,
    "has_phone": false
  },
  {
    "user_id": "26542503108767746",
    "phone": null,
    "has_phone": false
  },
  {
    "user_id": "35389449683979619",
    "phone": null,
    "has_phone": false
  },
  {
    "user_id": "27247005934900969",
    "phone": null,
    "has_phone": false
  },
  {
    "user_id": "26493307553701314",
    "phone": null,
    "has_phone": false
  },
  {
    "user_id": "26465259603169000",
    "phone": null,
    "has_phone": false
  },
  {
    "user_id": "26291432240545269",
    "phone": null,
    "has_phone": false
  },
  {
    "user_id": "26423265223974468",
    "phone": null,
    "has_phone": false
  },
  {
    "user_id": "27019408651018403",
    "phone": null,
    "has_phone": false
  },
  {
    "user_id": "27452355677686958",
    "phone": null,
    "has_phone": false
  },
  {
    "user_id": "35734521176138709",
    "phone": null,
    "has_phone": false
  },
  {
    "user_id": "25999078046460727",
    "phone": null,
    "has_phone": false
  },
  {
    "user_id": "25995874233427864",
    "phone": null,
    "has_phone": false
  },
  {
    "user_id": "26450433471289894",
    "phone": null,
    "has_phone": false
  },
  {
    "user_id": "26271337975894342",
    "phone": null,
    "has_phone": false
  },
  {
    "user_id": "26405939932392025",
    "phone": null,
    "has_phone": false
  },
  {
    "user_id": "27312723474982026",
    "phone": null,
    "has_phone": false
  },
  {
    "user_id": "25859988190346471",
    "phone": null,
    "has_phone": false
  },
  {
    "user_id": "26698192923148775",
    "phone": null,
    "has_phone": false
  },
  {
    "user_id": "35230087909938233",
    "phone": null,
    "has_phone": false
  },
  {
    "user_id": "27476396678626707",
    "phone": null,
    "has_phone": false
  },
  {
    "user_id": "26090485620652290",
    "phone": null,
    "has_phone": false
  },
  {
    "user_id": "25972016879166916",
    "phone": null,
    "has_phone": false
  },
  {
    "user_id": "26225229727140938",
    "phone": null,
    "has_phone": false
  },
  {
    "user_id": "26405274415762461",
    "phone": null,
    "has_phone": false
  },
  {
    "user_id": "35091381910507871",
    "phone": null,
    "has_phone": false
  },
  {
    "user_id": "26449068731425875",
    "phone": null,
    "has_phone": false
  },
  {
    "user_id": "26624919233768525",
    "phone": null,
    "has_phone": false
  },
  {
    "user_id": "26784561834471486",
    "phone": null,
    "has_phone": false
  },
  {
    "user_id": "26499604099724418",
    "phone": null,
    "has_phone": false
  },
  {
    "user_id": "26936931519226022",
    "phone": null,
    "has_phone": false
  },
  {
    "user_id": "26078166198546192",
    "phone": null,
    "has_phone": false
  },
  {
    "user_id": "26028668516836242",
    "phone": null,
    "has_phone": false
  },
  {
    "user_id": "26310232938597610",
    "phone": null,
    "has_phone": false
  },
  {
    "user_id": "26408122998854867",
    "phone": null,
    "has_phone": false
  },
  {
    "user_id": "35372447815686820",
    "phone": null,
    "has_phone": false
  },
  {
    "user_id": "27315181631418446",
    "phone": null,
    "has_phone": false
  },
  {
    "user_id": "24348058931558521",
    "phone": null,
    "has_phone": false
  },
  {
    "user_id": "26121740844164484",
    "phone": null,
    "has_phone": false
  },
  {
    "user_id": "26624172517212726",
    "phone": null,
    "has_phone": false
  },
  {
    "user_id": "26349177044742706",
    "phone": null,
    "has_phone": false
  },
  {
    "user_id": "26683727887930841",
    "phone": null,
    "has_phone": false
  },
  {
    "user_id": "26425160410473952",
    "phone": null,
    "has_phone": false
  },
  {
    "user_id": "35067222039589118",
    "phone": null,
    "has_phone": false
  },
  {
    "user_id": "26279545198393446",
    "phone": null,
    "has_phone": false
  },
  {
    "user_id": "26733870886224748",
    "phone": null,
    "has_phone": false
  },
  {
    "user_id": "26673552498924382",
    "phone": null,
    "has_phone": false
  },
  {
    "user_id": "26406813808972016",
    "phone": null,
    "has_phone": false
  },
  {
    "user_id": "27262412873360122",
    "phone": null,
    "has_phone": false
  },
  {
    "user_id": "26511059881893442",
    "phone": null,
    "has_phone": false
  },
  {
    "user_id": "26754174097552270",
    "phone": null,
    "has_phone": false
  },
  {
    "user_id": "26513693728249563",
    "phone": null,
    "has_phone": false
  },
  {
    "user_id": "27366060666315611",
    "phone": null,
    "has_phone": false
  },
  {
    "user_id": "26371977472467439",
    "phone": null,
    "has_phone": false
  },
  {
    "user_id": "26097267916640684",
    "phone": null,
    "has_phone": false
  },
  {
    "user_id": "26167795986256085",
    "phone": null,
    "has_phone": false
  },
  {
    "user_id": "35176599925286930",
    "phone": null,
    "has_phone": false
  },
  {
    "user_id": "26798705076380811",
    "phone": null,
    "has_phone": false
  },
  {
    "user_id": "24107925818904939",
    "phone": null,
    "has_phone": false
  },
  {
    "user_id": "26854080534246143",
    "phone": null,
    "has_phone": false
  },
  {
    "user_id": "35253264794287209",
    "phone": null,
    "has_phone": false
  },
  {
    "user_id": "26192942783708039",
    "phone": null,
    "has_phone": false
  },
  {
    "user_id": "26452376564416812",
    "phone": null,
    "has_phone": false
  },
  {
    "user_id": "26608010378833048",
    "phone": null,
    "has_phone": false
  },
  {
    "user_id": "26226396863729316",
    "phone": null,
    "has_phone": false
  },
  {
    "user_id": "24773905302307305",
    "phone": null,
    "has_phone": false
  },
  {
    "user_id": "26311937938491788",
    "phone": null,
    "has_phone": false
  },
  {
    "user_id": "25830502509961278",
    "phone": null,
    "has_phone": false
  },
  {
    "user_id": "27139798028960168",
    "phone": null,
    "has_phone": false
  },
  {
    "user_id": "27286091117659032",
    "phone": null,
    "has_phone": false
  },
  {
    "user_id": "27579712068285700",
    "phone": null,
    "has_phone": false
  },
  {
    "user_id": "26429701333362027",
    "phone": null,
    "has_phone": false
  },
  {
    "user_id": "26619529874346405",
    "phone": null,
    "has_phone": false
  },
  {
    "user_id": "26405578762416172",
    "phone": null,
    "has_phone": false
  },
  {
    "user_id": "25929101706768831",
    "phone": null,
    "has_phone": false
  },
  {
    "user_id": "27147331711535842",
    "phone": null,
    "has_phone": false
  },
  {
    "user_id": "35042460535368979",
    "phone": null,
    "has_phone": false
  },
  {
    "user_id": "34786908674227602",
    "phone": null,
    "has_phone": false
  },
  {
    "user_id": "27083954391197410",
    "phone": null,
    "has_phone": false
  },
  {
    "user_id": "26731471616488593",
    "phone": null,
    "has_phone": false
  },
  {
    "user_id": "26352233734388780",
    "phone": null,
    "has_phone": false
  },
  {
    "user_id": "26487433907581147",
    "phone": null,
    "has_phone": false
  },
  {
    "user_id": "26545997201705239",
    "phone": null,
    "has_phone": false
  },
  {
    "user_id": "26414225024903092",
    "phone": null,
    "has_phone": false
  },
  {
    "user_id": "26300731559585414",
    "phone": null,
    "has_phone": false
  },
  {
    "user_id": "25852423154437607",
    "phone": null,
    "has_phone": false
  },
  {
    "user_id": "26584533811155387",
    "phone": null,
    "has_phone": false
  },
  {
    "user_id": "26585924044394092",
    "phone": null,
    "has_phone": false
  },
  {
    "user_id": "26697494409888316",
    "phone": null,
    "has_phone": false
  },
  {
    "user_id": "27060849266848195",
    "phone": null,
    "has_phone": false
  },
  {
    "user_id": "26535739342711580",
    "phone": null,
    "has_phone": false
  },
  {
    "user_id": "26558206560507880",
    "phone": null,
    "has_phone": false
  },
  {
    "user_id": "26339516212372309",
    "phone": null,
    "has_phone": false
  },
  {
    "user_id": "35369478775976598",
    "phone": null,
    "has_phone": false
  },
  {
    "user_id": "26348110344852491",
    "phone": null,
    "has_phone": false
  },
  {
    "user_id": "25373796198961778",
    "phone": null,
    "has_phone": false
  },
  {
    "user_id": "26659748346970387",
    "phone": null,
    "has_phone": false
  },
  {
    "user_id": "34918398671139835",
    "phone": null,
    "has_phone": false
  },
  {
    "user_id": "26683135861320720",
    "phone": null,
    "has_phone": false
  },
  {
    "user_id": "26385737981037421",
    "phone": null,
    "has_phone": false
  },
  {
    "user_id": "26623229767273576",
    "phone": null,
    "has_phone": false
  },
  {
    "user_id": "25750906917917581",
    "phone": null,
    "has_phone": false
  },
  {
    "user_id": "26267621059567505",
    "phone": null,
    "has_phone": false
  },
  {
    "user_id": "26441035375548760",
    "phone": null,
    "has_phone": false
  },
  {
    "user_id": "26658548197117888",
    "phone": null,
    "has_phone": false
  },
  {
    "user_id": "34844581911856593",
    "phone": null,
    "has_phone": false
  },
  {
    "user_id": "24905405482490789",
    "phone": null,
    "has_phone": false
  },
  {
    "user_id": "26357667060553861",
    "phone": null,
    "has_phone": false
  },
  {
    "user_id": "27283612774574567",
    "phone": null,
    "has_phone": false
  },
  {
    "user_id": "26200474119654566",
    "phone": null,
    "has_phone": false
  },
  {
    "user_id": "34703729795942306",
    "phone": null,
    "has_phone": false
  },
  {
    "user_id": "35519735907624791",
    "phone": null,
    "has_phone": false
  },
  {
    "user_id": "26907694772161957",
    "phone": null,
    "has_phone": false
  },
  {
    "user_id": "27559782800277920",
    "phone": null,
    "has_phone": false
  },
  {
    "user_id": "26305479119101845",
    "phone": null,
    "has_phone": false
  },
  {
    "user_id": "26402862326039605",
    "phone": null,
    "has_phone": false
  },
  {
    "user_id": "26770090225961437",
    "phone": null,
    "has_phone": false
  },
  {
    "user_id": "26890747513864957",
    "phone": null,
    "has_phone": false
  },
  {
    "user_id": "26393361026992703",
    "phone": null,
    "has_phone": false
  },
  {
    "user_id": "35065047296441839",
    "phone": null,
    "has_phone": false
  },
  {
    "user_id": "27078181635098494",
    "phone": null,
    "has_phone": false
  },
  {
    "user_id": "26465334099766858",
    "phone": null,
    "has_phone": false
  },
  {
    "user_id": "35128444410132839",
    "phone": null,
    "has_phone": false
  },
  {
    "user_id": "26049814504690141",
    "phone": null,
    "has_phone": false
  },
  {
    "user_id": "34684834874496264",
    "phone": null,
    "has_phone": false
  },
  {
    "user_id": "26840740405523860",
    "phone": null,
    "has_phone": false
  },
  {
    "user_id": "34922255874088876",
    "phone": null,
    "has_phone": false
  },
  {
    "user_id": "25946160975065872",
    "phone": null,
    "has_phone": false
  },
  {
    "user_id": "35093500753597003",
    "phone": null,
    "has_phone": false
  },
  {
    "user_id": "26411100201832132",
    "phone": null,
    "has_phone": false
  },
  {
    "user_id": "25961448300218531",
    "phone": null,
    "has_phone": false
  },
  {
    "user_id": "26456256137362403",
    "phone": null,
    "has_phone": false
  },
  {
    "user_id": "27295479803387645",
    "phone": null,
    "has_phone": false
  },
  {
    "user_id": "26374150905588587",
    "phone": null,
    "has_phone": false
  },
  {
    "user_id": "26287631824238886",
    "phone": null,
    "has_phone": false
  },
  {
    "user_id": "26614282991537972",
    "phone": null,
    "has_phone": false
  },
  {
    "user_id": "26910331538585668",
    "phone": null,
    "has_phone": false
  },
  {
    "user_id": "26900812132838040",
    "phone": null,
    "has_phone": false
  },
  {
    "user_id": "26531195633237217",
    "phone": null,
    "has_phone": false
  },
  {
    "user_id": "26387578314274503",
    "phone": null,
    "has_phone": false
  },
  {
    "user_id": "26921500584117861",
    "phone": null,
    "has_phone": false
  },
  {
    "user_id": "26440743722203251",
    "phone": null,
    "has_phone": false
  },
  {
    "user_id": "26371979805745542",
    "phone": null,
    "has_phone": false
  },
  {
    "user_id": "34935761329401817",
    "phone": null,
    "has_phone": false
  },
  {
    "user_id": "26504720582488822",
    "phone": null,
    "has_phone": false
  },
  {
    "user_id": "26280610098232256",
    "phone": null,
    "has_phone": false
  },
  {
    "user_id": "26274055095576973",
    "phone": null,
    "has_phone": false
  },
  {
    "user_id": "26536512582632571",
    "phone": null,
    "has_phone": false
  },
  {
    "user_id": "27205804002370382",
    "phone": null,
    "has_phone": false
  },
  {
    "user_id": "27149660351293129",
    "phone": null,
    "has_phone": false
  },
  {
    "user_id": "26747234028221460",
    "phone": null,
    "has_phone": false
  },
  {
    "user_id": "35146161198332532",
    "phone": null,
    "has_phone": false
  },
  {
    "user_id": "35125338860446718",
    "phone": null,
    "has_phone": false
  },
  {
    "user_id": "27048707741393141",
    "phone": null,
    "has_phone": false
  },
  {
    "user_id": "26231189483220071",
    "phone": null,
    "has_phone": false
  },
  {
    "user_id": "26346309521676929",
    "phone": null,
    "has_phone": false
  },
  {
    "user_id": "26322405044084924",
    "phone": null,
    "has_phone": false
  },
  {
    "user_id": "27508638608726142",
    "phone": null,
    "has_phone": false
  },
  {
    "user_id": "26473120725659982",
    "phone": null,
    "has_phone": false
  },
  {
    "user_id": "25685946077744871",
    "phone": null,
    "has_phone": false
  },
  {
    "user_id": "26265917753031240",
    "phone": null,
    "has_phone": false
  },
  {
    "user_id": "27526266833628896",
    "phone": null,
    "has_phone": false
  },
  {
    "user_id": "26305725842454769",
    "phone": null,
    "has_phone": false
  },
  {
    "user_id": "35155903320721060",
    "phone": null,
    "has_phone": false
  },
  {
    "user_id": "26473204938998535",
    "phone": null,
    "has_phone": false
  },
  {
    "user_id": "26532335793097460",
    "phone": null,
    "has_phone": false
  },
  {
    "user_id": "26400124709642274",
    "phone": null,
    "has_phone": false
  },
  {
    "user_id": "26990417333883457",
    "phone": null,
    "has_phone": false
  },
  {
    "user_id": "35003779259237886",
    "phone": null,
    "has_phone": false
  },
  {
    "user_id": "26620588257553052",
    "phone": null,
    "has_phone": false
  },
  {
    "user_id": "26297422069927631",
    "phone": null,
    "has_phone": false
  },
  {
    "user_id": "26336233199393283",
    "phone": null,
    "has_phone": false
  },
  {
    "user_id": "34569721336007848",
    "phone": null,
    "has_phone": false
  },
  {
    "user_id": "26437679255874337",
    "phone": null,
    "has_phone": false
  },
  {
    "user_id": "26404534952538861",
    "phone": null,
    "has_phone": false
  },
  {
    "user_id": "26370761615915324",
    "phone": null,
    "has_phone": false
  },
  {
    "user_id": "26467276332914194",
    "phone": null,
    "has_phone": false
  },
  {
    "user_id": "26535978216068495",
    "phone": null,
    "has_phone": false
  },
  {
    "user_id": "26622860624013576",
    "phone": null,
    "has_phone": false
  },
  {
    "user_id": "24359833733714177",
    "phone": null,
    "has_phone": false
  },
  {
    "user_id": "26447096728234661",
    "phone": null,
    "has_phone": false
  },
  {
    "user_id": "26703337829298243",
    "phone": null,
    "has_phone": false
  },
  {
    "user_id": "35911890238398241",
    "phone": null,
    "has_phone": false
  },
  {
    "user_id": "26800028996316803",
    "phone": null,
    "has_phone": false
  },
  {
    "user_id": "26268284929531205",
    "phone": null,
    "has_phone": false
  },
  {
    "user_id": "26958186807107150",
    "phone": null,
    "has_phone": false
  },
  {
    "user_id": "34436671879312403",
    "phone": null,
    "has_phone": false
  },
  {
    "user_id": "26378190488511069",
    "phone": null,
    "has_phone": false
  },
  {
    "user_id": "34713082135003273",
    "phone": null,
    "has_phone": false
  },
  {
    "user_id": "26237392952557961",
    "phone": null,
    "has_phone": false
  },
  {
    "user_id": "26302503172732788",
    "phone": null,
    "has_phone": false
  },
  {
    "user_id": "26959616550296605",
    "phone": null,
    "has_phone": false
  },
  {
    "user_id": "26687746480861322",
    "phone": null,
    "has_phone": false
  },
  {
    "user_id": "25938229272545945",
    "phone": null,
    "has_phone": false
  },
  {
    "user_id": "34734088432906475",
    "phone": null,
    "has_phone": false
  },
  {
    "user_id": "27497336463200228",
    "phone": null,
    "has_phone": false
  },
  {
    "user_id": "25662656566742084",
    "phone": null,
    "has_phone": false
  },
  {
    "user_id": "26785780507708308",
    "phone": null,
    "has_phone": false
  },
  {
    "user_id": "26242474402070185",
    "phone": null,
    "has_phone": false
  },
  {
    "user_id": "25661177040223555",
    "phone": null,
    "has_phone": false
  },
  {
    "user_id": "24738587409173279",
    "phone": null,
    "has_phone": false
  },
  {
    "user_id": "34914177934896889",
    "phone": null,
    "has_phone": false
  },
  {
    "user_id": "26418274607832253",
    "phone": null,
    "has_phone": false
  },
  {
    "user_id": "26153437734338483",
    "phone": null,
    "has_phone": false
  },
  {
    "user_id": "26574996512119517",
    "phone": null,
    "has_phone": false
  },
  {
    "user_id": "35741332245457602",
    "phone": null,
    "has_phone": false
  },
  {
    "user_id": "26941547972129653",
    "phone": null,
    "has_phone": false
  },
  {
    "user_id": "26641937635415752",
    "phone": null,
    "has_phone": false
  },
  {
    "user_id": "26342280888759715",
    "phone": null,
    "has_phone": false
  },
  {
    "user_id": "26495320356819050",
    "phone": null,
    "has_phone": false
  },
  {
    "user_id": "27614426334811523",
    "phone": null,
    "has_phone": false
  },
  {
    "user_id": "34792997020347909",
    "phone": null,
    "has_phone": false
  },
  {
    "user_id": "26073285712372574",
    "phone": null,
    "has_phone": false
  },
  {
    "user_id": "26614552411564684",
    "phone": null,
    "has_phone": false
  },
  {
    "user_id": "26179082531772140",
    "phone": null,
    "has_phone": false
  },
  {
    "user_id": "26788141207469578",
    "phone": null,
    "has_phone": false
  },
  {
    "user_id": "26763040353325562",
    "phone": null,
    "has_phone": false
  },
  {
    "user_id": "27740848402183914",
    "phone": null,
    "has_phone": false
  },
  {
    "user_id": "26662405130022183",
    "phone": null,
    "has_phone": false
  },
  {
    "user_id": "34277909618523125",
    "phone": null,
    "has_phone": false
  },
  {
    "user_id": "26124664253899370",
    "phone": null,
    "has_phone": false
  },
  {
    "user_id": "26667630012853195",
    "phone": null,
    "has_phone": false
  },
  {
    "user_id": "35778264461760707",
    "phone": null,
    "has_phone": false
  },
  {
    "user_id": "26735146339434850",
    "phone": null,
    "has_phone": false
  },
  {
    "user_id": "27057998397141709",
    "phone": null,
    "has_phone": false
  },
  {
    "user_id": "26159993643683135",
    "phone": null,
    "has_phone": false
  },
  {
    "user_id": "26281057491586560",
    "phone": null,
    "has_phone": false
  },
  {
    "user_id": "26479725361689012",
    "phone": null,
    "has_phone": false
  },
  {
    "user_id": "26012378781763946",
    "phone": null,
    "has_phone": false
  },
  {
    "user_id": "34992902480325147",
    "phone": null,
    "has_phone": false
  },
  {
    "user_id": "27162862219982177",
    "phone": null,
    "has_phone": false
  },
  {
    "user_id": "25483961601306076",
    "phone": null,
    "has_phone": false
  },
  {
    "user_id": "26288847607442575",
    "phone": null,
    "has_phone": false
  },
  {
    "user_id": "35393690206882804",
    "phone": null,
    "has_phone": false
  },
  {
    "user_id": "35179218468358047",
    "phone": null,
    "has_phone": false
  },
  {
    "user_id": "25458472660495076",
    "phone": null,
    "has_phone": false
  },
  {
    "user_id": "26355231994118619",
    "phone": null,
    "has_phone": false
  },
  {
    "user_id": "26259229507096586",
    "phone": null,
    "has_phone": false
  },
  {
    "user_id": "26390490100612373",
    "phone": null,
    "has_phone": false
  },
  {
    "user_id": "27291547497096785",
    "phone": null,
    "has_phone": false
  },
  {
    "user_id": "26478161308503870",
    "phone": null,
    "has_phone": false
  },
  {
    "user_id": "26363095876683528",
    "phone": null,
    "has_phone": false
  },
  {
    "user_id": "25483371381338925",
    "phone": null,
    "has_phone": false
  },
  {
    "user_id": "27510769181844788",
    "phone": null,
    "has_phone": false
  },
  {
    "user_id": "35086998234281647",
    "phone": null,
    "has_phone": false
  },
  {
    "user_id": "25495241950149030",
    "phone": null,
    "has_phone": false
  },
  {
    "user_id": "25588342704173704",
    "phone": null,
    "has_phone": false
  },
  {
    "user_id": "26427073576947602",
    "phone": null,
    "has_phone": false
  },
  {
    "user_id": "27242756371978660",
    "phone": null,
    "has_phone": false
  },
  {
    "user_id": "26493666580298012",
    "phone": null,
    "has_phone": false
  },
  {
    "user_id": "26467968999564425",
    "phone": null,
    "has_phone": false
  },
  {
    "user_id": "26599634999702613",
    "phone": null,
    "has_phone": false
  },
  {
    "user_id": "26757957857226919",
    "phone": null,
    "has_phone": false
  },
  {
    "user_id": "26984937144464901",
    "phone": null,
    "has_phone": false
  },
  {
    "user_id": "26410966325227271",
    "phone": null,
    "has_phone": false
  },
  {
    "user_id": "26741610165462938",
    "phone": null,
    "has_phone": false
  },
  {
    "user_id": "26812692271704649",
    "phone": null,
    "has_phone": false
  },
  {
    "user_id": "26411078018546613",
    "phone": null,
    "has_phone": false
  },
  {
    "user_id": "35709609321959617",
    "phone": null,
    "has_phone": false
  },
  {
    "user_id": "26908683282102310",
    "phone": null,
    "has_phone": false
  },
  {
    "user_id": "26405914069066791",
    "phone": null,
    "has_phone": false
  },
  {
    "user_id": "26650524234559421",
    "phone": null,
    "has_phone": false
  },
  {
    "user_id": "26541985022103088",
    "phone": null,
    "has_phone": false
  },
  {
    "user_id": "26397088093307975",
    "phone": null,
    "has_phone": false
  },
  {
    "user_id": "25359325017076346",
    "phone": null,
    "has_phone": false
  },
  {
    "user_id": "26545228568450873",
    "phone": null,
    "has_phone": false
  },
  {
    "user_id": "26659910377009893",
    "phone": null,
    "has_phone": false
  },
  {
    "user_id": "26629721093382198",
    "phone": null,
    "has_phone": false
  },
  {
    "user_id": "26302786202690399",
    "phone": null,
    "has_phone": false
  },
  {
    "user_id": "26631654513191625",
    "phone": null,
    "has_phone": false
  },
  {
    "user_id": "27259240290345494",
    "phone": null,
    "has_phone": false
  },
  {
    "user_id": "26729913109965361",
    "phone": null,
    "has_phone": false
  },
  {
    "user_id": "26094954523509618",
    "phone": null,
    "has_phone": false
  },
  {
    "user_id": "26448506168150229",
    "phone": null,
    "has_phone": false
  },
  {
    "user_id": "26894246856859840",
    "phone": null,
    "has_phone": false
  },
  {
    "user_id": "27161994633397947",
    "phone": null,
    "has_phone": false
  },
  {
    "user_id": "27058052543798716",
    "phone": null,
    "has_phone": false
  },
  {
    "user_id": "26964474806503713",
    "phone": null,
    "has_phone": false
  },
  {
    "user_id": "26231917559824995",
    "phone": null,
    "has_phone": false
  },
  {
    "user_id": "26279362275062504",
    "phone": null,
    "has_phone": false
  },
  {
    "user_id": "34969352119345365",
    "phone": null,
    "has_phone": false
  },
  {
    "user_id": "27010515715212524",
    "phone": null,
    "has_phone": false
  },
  {
    "user_id": "35024386360510505",
    "phone": null,
    "has_phone": false
  },
  {
    "user_id": "26551236474514884",
    "phone": null,
    "has_phone": false
  },
  {
    "user_id": "26077123365323833",
    "phone": null,
    "has_phone": false
  },
  {
    "user_id": "26566589673031539",
    "phone": null,
    "has_phone": false
  },
  {
    "user_id": "26748558731443931",
    "phone": null,
    "has_phone": false
  },
  {
    "user_id": "26476047648724424",
    "phone": null,
    "has_phone": false
  },
  {
    "user_id": "26779795854978446",
    "phone": null,
    "has_phone": false
  },
  {
    "user_id": "26061634146826675",
    "phone": null,
    "has_phone": false
  },
  {
    "user_id": "26752883741012971",
    "phone": null,
    "has_phone": false
  },
  {
    "user_id": "26685490784471313",
    "phone": null,
    "has_phone": false
  },
  {
    "user_id": "26569009099382219",
    "phone": null,
    "has_phone": false
  },
  {
    "user_id": "26629486620026729",
    "phone": null,
    "has_phone": false
  },
  {
    "user_id": "35990538153878947",
    "phone": null,
    "has_phone": false
  },
  {
    "user_id": "26129314483437774",
    "phone": null,
    "has_phone": false
  },
  {
    "user_id": "27091584167114413",
    "phone": null,
    "has_phone": false
  },
  {
    "user_id": "27090935973852473",
    "phone": null,
    "has_phone": false
  },
  {
    "user_id": "26618598517770316",
    "phone": null,
    "has_phone": false
  },
  {
    "user_id": "26440164185637554",
    "phone": null,
    "has_phone": false
  },
  {
    "user_id": "26482580724766304",
    "phone": null,
    "has_phone": false
  },
  {
    "user_id": "26362860563332066",
    "phone": null,
    "has_phone": false
  },
  {
    "user_id": "26679135468370267",
    "phone": null,
    "has_phone": false
  },
  {
    "user_id": "34827680230209944",
    "phone": null,
    "has_phone": false
  },
  {
    "user_id": "27051791617752436",
    "phone": null,
    "has_phone": false
  },
  {
    "user_id": "26918457701105865",
    "phone": null,
    "has_phone": false
  },
  {
    "user_id": "26264899886470096",
    "phone": null,
    "has_phone": false
  },
  {
    "user_id": "26587644294198236",
    "phone": null,
    "has_phone": false
  },
  {
    "user_id": "26187563204235513",
    "phone": null,
    "has_phone": false
  },
  {
    "user_id": "26322397514111570",
    "phone": null,
    "has_phone": false
  },
  {
    "user_id": "26575357232083412",
    "phone": null,
    "has_phone": false
  },
  {
    "user_id": "26416538861328745",
    "phone": null,
    "has_phone": false
  },
  {
    "user_id": "26295281980161826",
    "phone": null,
    "has_phone": false
  },
  {
    "user_id": "26210715671960828",
    "phone": null,
    "has_phone": false
  },
  {
    "user_id": "26465476669738785",
    "phone": null,
    "has_phone": false
  },
  {
    "user_id": "34745674808412641",
    "phone": null,
    "has_phone": false
  },
  {
    "user_id": "25797636443249086",
    "phone": null,
    "has_phone": false
  },
  {
    "user_id": "26564713136495365",
    "phone": null,
    "has_phone": false
  },
  {
    "user_id": "26218610451171673",
    "phone": null,
    "has_phone": false
  },
  {
    "user_id": "26530982283189093",
    "phone": null,
    "has_phone": false
  },
  {
    "user_id": "26328977233463030",
    "phone": null,
    "has_phone": false
  },
  {
    "user_id": "26291922167131973",
    "phone": null,
    "has_phone": false
  },
  {
    "user_id": "35025964430351230",
    "phone": null,
    "has_phone": false
  },
  {
    "user_id": "26414996504824979",
    "phone": null,
    "has_phone": false
  },
  {
    "user_id": "26509377518702029",
    "phone": null,
    "has_phone": false
  },
  {
    "user_id": "26598535046462217",
    "phone": null,
    "has_phone": false
  },
  {
    "user_id": "26919497604321790",
    "phone": null,
    "has_phone": false
  },
  {
    "user_id": "26828044653487053",
    "phone": null,
    "has_phone": false
  },
  {
    "user_id": "26494514526880430",
    "phone": null,
    "has_phone": false
  },
  {
    "user_id": "26188297060781097",
    "phone": null,
    "has_phone": false
  },
  {
    "user_id": "26859889650281515",
    "phone": null,
    "has_phone": false
  },
  {
    "user_id": "26334616796219565",
    "phone": null,
    "has_phone": false
  },
  {
    "user_id": "27369835589272422",
    "phone": null,
    "has_phone": false
  },
  {
    "user_id": "26261639250197377",
    "phone": null,
    "has_phone": false
  },
  {
    "user_id": "36114720211460144",
    "phone": null,
    "has_phone": false
  },
  {
    "user_id": "26600047262995483",
    "phone": null,
    "has_phone": false
  },
  {
    "user_id": "26278972968449503",
    "phone": null,
    "has_phone": false
  },
  {
    "user_id": "26480436421647190",
    "phone": null,
    "has_phone": false
  },
  {
    "user_id": "25753454767660865",
    "phone": null,
    "has_phone": false
  },
  {
    "user_id": "26371010375924662",
    "phone": null,
    "has_phone": false
  },
  {
    "user_id": "26572026665770734",
    "phone": null,
    "has_phone": false
  },
  {
    "user_id": "26077891201840101",
    "phone": null,
    "has_phone": false
  },
  {
    "user_id": "34862670246711981",
    "phone": null,
    "has_phone": false
  },
  {
    "user_id": "26221492934199217",
    "phone": null,
    "has_phone": false
  },
  {
    "user_id": "26464863516507256",
    "phone": null,
    "has_phone": false
  },
  {
    "user_id": "26544916931788058",
    "phone": null,
    "has_phone": false
  },
  {
    "user_id": "26957847157221239",
    "phone": null,
    "has_phone": false
  },
  {
    "user_id": "26273466385615567",
    "phone": null,
    "has_phone": false
  },
  {
    "user_id": "26633038159694635",
    "phone": null,
    "has_phone": false
  },
  {
    "user_id": "26192268973778712",
    "phone": null,
    "has_phone": false
  },
  {
    "user_id": "26888776120726762",
    "phone": null,
    "has_phone": false
  },
  {
    "user_id": "26239515355700080",
    "phone": null,
    "has_phone": false
  },
  {
    "user_id": "26372578835686001",
    "phone": null,
    "has_phone": false
  },
  {
    "user_id": "26377582751892872",
    "phone": null,
    "has_phone": false
  },
  {
    "user_id": "26390355477273018",
    "phone": null,
    "has_phone": false
  },
  {
    "user_id": "25970035179332569",
    "phone": null,
    "has_phone": false
  },
  {
    "user_id": "26785282031103525",
    "phone": null,
    "has_phone": false
  },
  {
    "user_id": "26056602677369282",
    "phone": null,
    "has_phone": false
  },
  {
    "user_id": "26362449546750119",
    "phone": null,
    "has_phone": false
  },
  {
    "user_id": "34821497567496595",
    "phone": null,
    "has_phone": false
  },
  {
    "user_id": "26229869146635409",
    "phone": null,
    "has_phone": false
  },
  {
    "user_id": "27015636101366215",
    "phone": null,
    "has_phone": false
  },
  {
    "user_id": "36005655679034006",
    "phone": null,
    "has_phone": false
  },
  {
    "user_id": "26817387317865172",
    "phone": null,
    "has_phone": false
  },
  {
    "user_id": "25541482808858034",
    "phone": null,
    "has_phone": false
  },
  {
    "user_id": "26296363210057545",
    "phone": null,
    "has_phone": false
  },
  {
    "user_id": "26535662382740846",
    "phone": null,
    "has_phone": false
  },
  {
    "user_id": "26225798703738274",
    "phone": null,
    "has_phone": false
  },
  {
    "user_id": "26640451605589436",
    "phone": null,
    "has_phone": false
  },
  {
    "user_id": "34769864245961781",
    "phone": null,
    "has_phone": false
  },
  {
    "user_id": "25987034294304658",
    "phone": null,
    "has_phone": false
  },
  {
    "user_id": "26442970835322140",
    "phone": null,
    "has_phone": false
  },
  {
    "user_id": "26338576915805551",
    "phone": null,
    "has_phone": false
  },
  {
    "user_id": "24977702335261394",
    "phone": null,
    "has_phone": false
  },
  {
    "user_id": "27079475378344870",
    "phone": null,
    "has_phone": false
  },
  {
    "user_id": "26625315727135169",
    "phone": null,
    "has_phone": false
  },
  {
    "user_id": "34872391872405686",
    "phone": null,
    "has_phone": false
  },
  {
    "user_id": "34915745698040843",
    "phone": null,
    "has_phone": false
  },
  {
    "user_id": "26432410473091672",
    "phone": null,
    "has_phone": false
  },
  {
    "user_id": "26598538519758752",
    "phone": null,
    "has_phone": false
  },
  {
    "user_id": "34896117530003236",
    "phone": null,
    "has_phone": false
  },
  {
    "user_id": "26073002645729181",
    "phone": null,
    "has_phone": false
  },
  {
    "user_id": "26413940324956091",
    "phone": null,
    "has_phone": false
  },
  {
    "user_id": "26640391158963700",
    "phone": null,
    "has_phone": false
  },
  {
    "user_id": "27242209482050011",
    "phone": null,
    "has_phone": false
  },
  {
    "user_id": "26087894220893772",
    "phone": null,
    "has_phone": false
  },
  {
    "user_id": "26565657486455898",
    "phone": null,
    "has_phone": false
  },
  {
    "user_id": "35515570951359694",
    "phone": null,
    "has_phone": false
  },
  {
    "user_id": "26523557590642315",
    "phone": null,
    "has_phone": false
  },
  {
    "user_id": "26411929461828889",
    "phone": null,
    "has_phone": false
  },
  {
    "user_id": "26495215190121321",
    "phone": null,
    "has_phone": false
  },
  {
    "user_id": "25804286559246687",
    "phone": null,
    "has_phone": false
  },
  {
    "user_id": "27448818661384483",
    "phone": null,
    "has_phone": false
  },
  {
    "user_id": "26035597902800843",
    "phone": null,
    "has_phone": false
  },
  {
    "user_id": "26541752018810986",
    "phone": null,
    "has_phone": false
  },
  {
    "user_id": "26971872075730719",
    "phone": null,
    "has_phone": false
  },
  {
    "user_id": "26526480936994484",
    "phone": null,
    "has_phone": false
  },
  {
    "user_id": "26598942563095744",
    "phone": null,
    "has_phone": false
  },
  {
    "user_id": "26924995527103947",
    "phone": null,
    "has_phone": false
  },
  {
    "user_id": "26945325848407875",
    "phone": null,
    "has_phone": false
  },
  {
    "user_id": "26598748789756808",
    "phone": null,
    "has_phone": false
  },
  {
    "user_id": "27271529889115844",
    "phone": null,
    "has_phone": false
  },
  {
    "user_id": "26322859044039968",
    "phone": "+201271259141",
    "has_phone": true
  },
  {
    "user_id": "26613839101639431",
    "phone": null,
    "has_phone": false
  },
  {
    "user_id": "34924943903757379",
    "phone": null,
    "has_phone": false
  },
  {
    "user_id": "26104066892609136",
    "phone": null,
    "has_phone": false
  },
  {
    "user_id": "26411234318530214",
    "phone": null,
    "has_phone": false
  },
  {
    "user_id": "26407026825587020",
    "phone": null,
    "has_phone": false
  },
  {
    "user_id": "35341470375466733",
    "phone": null,
    "has_phone": false
  },
  {
    "user_id": "26363563229932634",
    "phone": null,
    "has_phone": false
  },
  {
    "user_id": "26702540982709659",
    "phone": null,
    "has_phone": false
  },
  {
    "user_id": "26498830676473634",
    "phone": null,
    "has_phone": false
  },
  {
    "user_id": "26978673225067872",
    "phone": null,
    "has_phone": false
  },
  {
    "user_id": "26461104130151182",
    "phone": null,
    "has_phone": false
  },
  {
    "user_id": "26254825427483623",
    "phone": null,
    "has_phone": false
  },
  {
    "user_id": "26335612856132700",
    "phone": null,
    "has_phone": false
  },
  {
    "user_id": "26360929403591854",
    "phone": null,
    "has_phone": false
  },
  {
    "user_id": "26505467289074617",
    "phone": null,
    "has_phone": false
  },
  {
    "user_id": "34930221546623538",
    "phone": null,
    "has_phone": false
  },
  {
    "user_id": "26477338308598981",
    "phone": null,
    "has_phone": false
  },
  {
    "user_id": "34881822531432004",
    "phone": null,
    "has_phone": false
  },
  {
    "user_id": "27563947886529169",
    "phone": null,
    "has_phone": false
  },
  {
    "user_id": "34988116360834810",
    "phone": null,
    "has_phone": false
  },
  {
    "user_id": "26639846312312245",
    "phone": null,
    "has_phone": false
  },
  {
    "user_id": "27083163324710051",
    "phone": null,
    "has_phone": false
  },
  {
    "user_id": "34795151170131586",
    "phone": null,
    "has_phone": false
  },
  {
    "user_id": "26447995721553454",
    "phone": null,
    "has_phone": false
  },
  {
    "user_id": "27575385298716742",
    "phone": null,
    "has_phone": false
  },
  {
    "user_id": "26416525678010569",
    "phone": null,
    "has_phone": false
  },
  {
    "user_id": "26360717770255193",
    "phone": null,
    "has_phone": false
  },
  {
    "user_id": "27177691055167495",
    "phone": null,
    "has_phone": false
  },
  {
    "user_id": "26331641289796187",
    "phone": null,
    "has_phone": false
  },
  {
    "user_id": "26646645188298360",
    "phone": null,
    "has_phone": false
  },
  {
    "user_id": "26321197330898355",
    "phone": null,
    "has_phone": false
  },
  {
    "user_id": "26655059907453044",
    "phone": null,
    "has_phone": false
  },
  {
    "user_id": "35400878442836818",
    "phone": null,
    "has_phone": false
  },
  {
    "user_id": "26524331957186501",
    "phone": null,
    "has_phone": false
  },
  {
    "user_id": "26520130810953261",
    "phone": null,
    "has_phone": false
  },
  {
    "user_id": "27413749648227673",
    "phone": null,
    "has_phone": false
  },
  {
    "user_id": "26655613760792643",
    "phone": null,
    "has_phone": false
  },
  {
    "user_id": "27440972442169779",
    "phone": null,
    "has_phone": false
  },
  {
    "user_id": "35344177935173586",
    "phone": null,
    "has_phone": false
  },
  {
    "user_id": "26773462608937518",
    "phone": null,
    "has_phone": false
  },
  {
    "user_id": "34742721345376480",
    "phone": null,
    "has_phone": false
  },
  {
    "user_id": "26682043761411949",
    "phone": null,
    "has_phone": false
  },
  {
    "user_id": "35217091834570758",
    "phone": null,
    "has_phone": false
  },
  {
    "user_id": "26487995840899726",
    "phone": null,
    "has_phone": false
  },
  {
    "user_id": "25958019910542283",
    "phone": null,
    "has_phone": false
  },
  {
    "user_id": "26376549085334867",
    "phone": null,
    "has_phone": false
  },
  {
    "user_id": "26364347256554065",
    "phone": null,
    "has_phone": false
  },
  {
    "user_id": "25802443489435519",
    "phone": null,
    "has_phone": false
  },
  {
    "user_id": "26759903260301855",
    "phone": null,
    "has_phone": false
  },
  {
    "user_id": "27175486468701599",
    "phone": null,
    "has_phone": false
  },
  {
    "user_id": "27122669880671700",
    "phone": null,
    "has_phone": false
  },
  {
    "user_id": "25051880024510271",
    "phone": null,
    "has_phone": false
  },
  {
    "user_id": "27000803099503882",
    "phone": null,
    "has_phone": false
  },
  {
    "user_id": "27433785096210901",
    "phone": null,
    "has_phone": false
  },
  {
    "user_id": "27599332782989820",
    "phone": null,
    "has_phone": false
  },
  {
    "user_id": "26264879579801171",
    "phone": null,
    "has_phone": false
  },
  {
    "user_id": "26473709848962746",
    "phone": null,
    "has_phone": false
  },
  {
    "user_id": "26685285977756637",
    "phone": null,
    "has_phone": false
  },
  {
    "user_id": "25513386161670557",
    "phone": null,
    "has_phone": false
  },
  {
    "user_id": "26376868048674776",
    "phone": null,
    "has_phone": false
  },
  {
    "user_id": "25997380739872508",
    "phone": null,
    "has_phone": false
  },
  {
    "user_id": "26314114538211365",
    "phone": null,
    "has_phone": false
  },
  {
    "user_id": "36123100070621998",
    "phone": null,
    "has_phone": false
  },
  {
    "user_id": "26256230090715438",
    "phone": null,
    "has_phone": false
  },
  {
    "user_id": "26991674220430404",
    "phone": null,
    "has_phone": false
  },
  {
    "user_id": "26578688651795660",
    "phone": null,
    "has_phone": false
  },
  {
    "user_id": "26369006496128003",
    "phone": null,
    "has_phone": false
  },
  {
    "user_id": "26644760378461406",
    "phone": null,
    "has_phone": false
  },
  {
    "user_id": "34941920455454107",
    "phone": null,
    "has_phone": false
  },
  {
    "user_id": "26518775011086765",
    "phone": null,
    "has_phone": false
  },
  {
    "user_id": "26277330775291164",
    "phone": null,
    "has_phone": false
  },
  {
    "user_id": "26279185958440887",
    "phone": null,
    "has_phone": false
  },
  {
    "user_id": "26490692097249929",
    "phone": null,
    "has_phone": false
  },
  {
    "user_id": "26152636337689729",
    "phone": null,
    "has_phone": false
  },
  {
    "user_id": "26421526717515413",
    "phone": null,
    "has_phone": false
  },
  {
    "user_id": "26676161025353364",
    "phone": null,
    "has_phone": false
  },
  {
    "user_id": "34317296434552701",
    "phone": null,
    "has_phone": false
  },
  {
    "user_id": "26890327850552671",
    "phone": null,
    "has_phone": false
  },
  {
    "user_id": "25484196367923165",
    "phone": null,
    "has_phone": false
  },
  {
    "user_id": "26007391408909794",
    "phone": null,
    "has_phone": false
  },
  {
    "user_id": "26579961208332998",
    "phone": null,
    "has_phone": false
  },
  {
    "user_id": "26912405275059536",
    "phone": null,
    "has_phone": false
  },
  {
    "user_id": "34952351977713915",
    "phone": null,
    "has_phone": false
  },
  {
    "user_id": "26719387591033423",
    "phone": null,
    "has_phone": false
  },
  {
    "user_id": "26506631985697559",
    "phone": null,
    "has_phone": false
  },
  {
    "user_id": "26102911722724317",
    "phone": null,
    "has_phone": false
  },
  {
    "user_id": "35936760275923182",
    "phone": null,
    "has_phone": false
  },
  {
    "user_id": "25561378090205654",
    "phone": null,
    "has_phone": false
  },
  {
    "user_id": "26337860252537333",
    "phone": null,
    "has_phone": false
  },
  {
    "user_id": "26478847478401372",
    "phone": null,
    "has_phone": false
  },
  {
    "user_id": "26466454753016630",
    "phone": null,
    "has_phone": false
  },
  {
    "user_id": "26319637607678337",
    "phone": null,
    "has_phone": false
  },
  {
    "user_id": "26682521271388094",
    "phone": null,
    "has_phone": false
  },
  {
    "user_id": "27023034123949160",
    "phone": null,
    "has_phone": false
  },
  {
    "user_id": "26956372557299736",
    "phone": null,
    "has_phone": false
  },
  {
    "user_id": "24528321756865478",
    "phone": null,
    "has_phone": false
  },
  {
    "user_id": "26269887172680748",
    "phone": null,
    "has_phone": false
  },
  {
    "user_id": "26795464453411783",
    "phone": null,
    "has_phone": false
  },
  {
    "user_id": "26470082665978592",
    "phone": null,
    "has_phone": false
  },
  {
    "user_id": "26642111682066150",
    "phone": null,
    "has_phone": false
  },
  {
    "user_id": "27633964869537270",
    "phone": null,
    "has_phone": false
  },
  {
    "user_id": "26515093931459978",
    "phone": null,
    "has_phone": false
  },
  {
    "user_id": "34968040996176669",
    "phone": null,
    "has_phone": false
  },
  {
    "user_id": "26371155732576007",
    "phone": null,
    "has_phone": false
  },
  {
    "user_id": "26089910740707772",
    "phone": null,
    "has_phone": false
  },
  {
    "user_id": "27062040396727309",
    "phone": null,
    "has_phone": false
  },
  {
    "user_id": "26832923342999291",
    "phone": null,
    "has_phone": false
  },
  {
    "user_id": "26405315265756219",
    "phone": null,
    "has_phone": false
  },
  {
    "user_id": "26203230239347599",
    "phone": null,
    "has_phone": false
  },
  {
    "user_id": "26962143513372123",
    "phone": null,
    "has_phone": false
  },
  {
    "user_id": "27317521137836903",
    "phone": null,
    "has_phone": false
  },
  {
    "user_id": "26659225767063710",
    "phone": null,
    "has_phone": false
  },
  {
    "user_id": "26992139807077799",
    "phone": null,
    "has_phone": false
  },
  {
    "user_id": "35036354956008844",
    "phone": null,
    "has_phone": false
  },
  {
    "user_id": "26729154993441800",
    "phone": null,
    "has_phone": false
  },
  {
    "user_id": "34895098040136620",
    "phone": null,
    "has_phone": false
  },
  {
    "user_id": "27073149892285842",
    "phone": null,
    "has_phone": false
  },
  {
    "user_id": "26110591908592827",
    "phone": null,
    "has_phone": false
  },
  {
    "user_id": "34986488650966753",
    "phone": null,
    "has_phone": false
  },
  {
    "user_id": "34806469515664317",
    "phone": null,
    "has_phone": false
  },
  {
    "user_id": "26852606664334798",
    "phone": null,
    "has_phone": false
  },
  {
    "user_id": "34975778982070552",
    "phone": null,
    "has_phone": false
  }
]